{
  "@type": "activity",
  "achievement_count": 10,
  "athlete_count": 2,
  "athlete_id": 129012597,
  "average_cadence": 0,
  "average_heartrate": 149,
  "average_speed": 2.509,
  "average_watts": 0,
  "calories": 0,
  "comment_count": 0,
  "commute": 0,
  "description": null,
  "device_name": null,
  "device_watts": 0,
  "distance": 10060.9,
  "elapsed_time": 4201,
  "end_lat": 52.525485986843705,
  "end_lng": 13.410881711170077,
  "flagged": 0,
  "gear_id": "g16634171",
  "has_heartrate": 1,
  "id": "12214152949",
  "kilojoules": 0,
  "kudos_count": 0,
  "manual": 0,
  "max_heartrate": 172,
  "max_speed": 4.888,
  "max_watts": 0,
  "moving_time": 4010,
  "name": "Course à pied le matin",
  "p_activity_type": "Run",
  "p_bug_score": 0,
  "p_has_bug": 0,
  "p_has_duplicate": 1,
  "photo_count": 0,
  "pr_count": 7,
  "private": 1,
  "raw_json": {
    "achievement_count": 10,
    "athlete": {
      "id": 129012597,
      "resource_state": 1
    },
    "athlete_count": 2,
    "average_heartrate": 149,
    "average_speed": 2.509,
    "comment_count": 0,
    "commute": false,
    "device_name": "Apple Watch Ultra 2",
    "display_hide_heartrate_option": true,
    "distance": 10060.9,
    "elapsed_time": 4201,
    "elev_high": 42.2,
    "elev_low": 32.3,
    "end_latlng": [
      52.525485986843705,
      13.410881711170077
    ],
    "external_id": "B7D75153-2319-4B8B-851B-B016340842AE.fit",
    "flagged": false,
    "from_accepted_tag": false,
    "gear_id": "g16634171",
    "has_heartrate": true,
    "has_kudoed": false,
    "heartrate_opt_out": false,
    "id": 12214152949,
    "kudos_count": 0,
    "location_city": null,
    "location_country": null,
    "location_state": null,
    "manual": false,
    "map": {
      "id": "a12214152949",
      "resource_state": 2,
      "summary_polyline": "}tq_IaxypAId@JP?J{@jCQz@It@Bt@VbBd@~D@lAO~D?^NVTThBt@j@PJLPh@Ax@Dh@P\\Rh@p@jCb@~@Tr@JFZCPIPUNGPA\\TP@DFLv@HNHJl@b@HDFADO@o@g@eBKMYO_@GG?C@ABBBLA`@KH?h@PV@LCVOl@Gr@Wb@W`@e@fBeBfBsAf@u@LMJIF@DBFJd@|A`A|DHf@?VId@Hj@Vt@V`ATl@\\r@J`@HnBR~GDdD^bO?fAAbA@tAj@zVZxKPbIJzCFv@H`@Dh@@fA?xCHzCPrG`@fFRlFDtB?v@CFZG\\SNSNe@LWLKTE|@CdCPV?TADKd@CNKNGlB@h@@TFHLNr@b@AvBRjL~Al@?ZGFGBQFkCMgGm@uWA{BF}@FUV]ZSjGcCxAq@fAi@hHwClAo@nAc@XQI[IEsD~Ac@HGAEOq@sRQyJe@wO[cOMqC?i@H_BEK]Uz@oDz@sEj@cD\\oCAc@Be@CYQs@g@}@Wi@EQ@MBKLIz@g@b@KZYHQF]L_A@[Hc@R]d@}AHIVMDIz@{EjA}FzBmLNcA?e@C]U_@a@Oy@k@_@OWSWOi@o@MYE_@OSgAi@_@WmB}As@m@SW_B_AkAeAy@k@]OKJEL@CAC[k@OQqAgAyAeA_@S{@YyBaBSUQB[MQAG@U`@GCa@a@?IDs@CGUO[i@SOe@WcE{AoE{Ac@Ei@FyCQY?c@Oa@C]GEE@GL{A[Es@S{@J_BE{@?s@DmBToBn@YNgExCeAz@iCrD}@fASRG@C?IKOAo@u@qAcAMc@Yo@w@y@GEE?{@lCo@~BIRODw@vBOj@_@lAYf@cBzEWj@KFGEW_@YU{A_Bg@c@C@M\\U~@"
    },
    "max_heartrate": 172,
    "max_speed": 4.888,
    "moving_time": 4010,
    "name": "Course à pied le matin",
    "photo_count": 0,
    "pr_count": 7,
    "private": true,
    "resource_state": 2,
    "sport_type": "Run",
    "start_date": "2024-08-20T03:48:01Z",
    "start_date_local": "2024-08-20T05:48:01Z",
    "start_latlng": [
      52.524497509002686,
      13.409869177266955
    ],
    "suffer_score": 87,
    "timezone": "(GMT+01:00) Europe/Berlin",
    "total_elevation_gain": 18.7,
    "total_photo_count": 0,
    "trainer": false,
    "type": "Run",
    "upload_id": 13021507939,
    "upload_id_str": "13021507939",
    "utc_offset": 7200,
    "visibility": "only_me",
    "workout_type": null
  },
  "sport_type": "Run",
  "start_date": "2024-08-20T03:48:01Z",
  "start_date_local": "2024-08-20T05:48:01Z",
  "start_lat": 52.524497509002686,
  "start_lng": 13.409869177266955,
  "suffer_score": 87,
  "timezone": "(GMT+01:00) Europe/Berlin",
  "total_elevation_gain": 18.7,
  "trainer": 0,
  "type": "Run",
  "visibility": "only_me",
  "weighted_average_watts": 0,
  "workout_type": null
}