{
  "@type": "activity",
  "achievement_count": 0,
  "athlete": {
    "id": 129012597,
    "resource_state": 1
  },
  "athlete_count": 1,
  "average_cadence": 92.9,
  "average_heartrate": 144.8,
  "average_speed": 2.436,
  "average_watts": 231.8,
  "comment_count": 1,
  "commute": false,
  "device_name": "Garmin fēnix 7",
  "device_watts": true,
  "display_hide_heartrate_option": true,
  "distance": 1488.6,
  "elapsed_time": 650,
  "elev_high": 23,
  "elev_low": 11.4,
  "end_latlng": [
    49.43936797790229,
    1.0792344063520432
  ],
  "external_id": "garmin_ping_366838020864",
  "flagged": false,
  "from_accepted_tag": false,
  "gear_id": "g17703203",
  "has_heartrate": true,
  "has_kudoed": false,
  "heartrate_opt_out": false,
  "id": "12295428213",
  "kilojoules": 143.6,
  "kudos_count": 3,
  "location_city": null,
  "location_country": null,
  "location_state": null,
  "manual": false,
  "map": {
    "id": "a12295428213",
    "resource_state": 2,
    "summary_polyline": "mxwlHeitEP@QtAM\\DJCVBRFFd@RPNHB`@ZHRNPP\\LNNJTCFB\\\\j@VdAt@R?VJh@Zx@^V@ZEFJh@h@\\T^NNJZFr@DHDEJ?INDzA`Av@\\jBbAv@Z|@n@FL@TSj@kAdH[lACTWr@MTiBpEGZ[|@k@bC_@dCYpAu@fFo@|CATBRBH^^BL?L"
  },
  "max_heartrate": 166,
  "max_speed": 5.432,
  "max_watts": 366,
  "moving_time": 611,
  "name": "Course à pied avec sac à dos",
  "photo_count": 0,
  "pr_count": 0,
  "private": false,
  "resource_state": 2,
  "sport_type": "Run",
  "start_date": "2024-09-01T08:07:11Z",
  "start_date_local": "2024-09-01T10:07:11Z",
  "start_latlng": [
    49.44279910996556,
    1.0921981930732727
  ],
  "suffer_score": 4,
  "timezone": "(GMT+01:00) Europe/Paris",
  "total_elevation_gain": 3,
  "total_photo_count": 1,
  "trainer": false,
  "type": "Run",
  "upload_id": 13107028349,
  "upload_id_str": "13107028349",
  "utc_offset": 7200,
  "visibility": "followers_only",
  "weighted_average_watts": 220,
  "workout_type": 0
}