{
  "@type": "activity",
  "achievement_count": 0,
  "athlete": {
    "id": 129012597,
    "resource_state": 1
  },
  "athlete_count": 1,
  "average_heartrate": 106.3,
  "average_speed": 0,
  "comment_count": 0,
  "commute": false,
  "device_name": "WHOOP",
  "display_hide_heartrate_option": true,
  "distance": 0,
  "elapsed_time": 4259,
  "elev_high": 0,
  "elev_low": 0,
  "end_latlng": [],
  "external_id": "ExampleSettings.fit",
  "flagged": false,
  "from_accepted_tag": false,
  "gear_id": null,
  "has_heartrate": true,
  "has_kudoed": false,
  "heartrate_opt_out": false,
  "id": "12661956849",
  "kudos_count": 7,
  "location_city": null,
  "location_country": null,
  "location_state": null,
  "manual": false,
  "map": {
    "id": "a12661956849",
    "resource_state": 2,
    "summary_polyline": ""
  },
  "max_heartrate": 147,
  "max_speed": 0,
  "moving_time": 4259,
  "name": "Renfo avec Maxime #5",
  "photo_count": 0,
  "pr_count": 0,
  "private": false,
  "resource_state": 2,
  "sport_type": "WeightTraining",
  "start_date": "2024-10-15T12:30:00Z",
  "start_date_local": "2024-10-15T14:30:00Z",
  "start_latlng": [],
  "suffer_score": 10,
  "timezone": "(GMT+01:00) Europe/Paris",
  "total_elevation_gain": 0,
  "total_photo_count": 1,
  "trainer": true,
  "type": "WeightTraining",
  "upload_id": 13499948747,
  "upload_id_str": "13499948747",
  "utc_offset": 7200,
  "visibility": "followers_only",
  "workout_type": 30
}